SimpleMLP/__init__.py
SimpleMLP/network.py
SimpleMLP/value.py
SimpleMLP-1.0.1.dist-info/LICENCE
SimpleMLP-1.0.1.dist-info/METADATA
SimpleMLP-1.0.1.dist-info/WHEEL
SimpleMLP-1.0.1.dist-info/top_level.txt
SimpleMLP-1.0.1.dist-info/RECORD
